{
    "==Final Doubles Bracket==": {
        "l1m1": {
            "t1p1": "DJ Nintendo",
            "t1p1flag": "us",
            "t1p2": "The Moon",
            "t1p2flag": "us",
            "t1score": "win",
            "t2p1": "Ryobeat",
            "t2p1flag": "us",
            "t2p2": "Captain Smuckers",
            "t2p2flag": "us",
            "t2score": "",
            "win": "1"
        },
        "r1m1": {
            "t1p1": "Animal",
            "t1p1flag": "us",
            "t1p2": "G$",
            "t1p2flag": "us",
            "t1score": "1",
            "t2p1": "Swedish Delight",
            "t2p1flag": "us",
            "t2p2": "Slox",
            "t2p2flag": "us",
            "t2score": "3",
            "win": "2"
        },
        "r2m1": {
            "t1p1": "Animal",
            "t1p1flag": "us",
            "t1p2": "G$",
            "t1p2flag": "us",
            "t1score": "",
            "t2p1": "DJ Nintendo",
            "t2p1flag": "us",
            "t2p2": "The Moon",
            "t2p2flag": "us",
            "t2score": "win",
            "win": "2"
        },
        "r3m1": {
            "t1p1": "Swedish Delight",
            "t1p1flag": "us",
            "t1p2": "Slox",
            "t1p2flag": "us",
            "t1score": "3",
            "t2p1": "DJ Nintendo",
            "t2p1flag": "us",
            "t2p2": "The Moon",
            "t2p2flag": "us",
            "t2score": "2",
            "win": "1"
        }
    },
    "==Losers Bracket==": {
        "l1m1": {
            "t1p1": "Bye",
            "t1p1flag": "",
            "t1p2": "Bye",
            "t1p2flag": "",
            "t1score": "",
            "t2p1": "SB Noya",
            "t2p1flag": "",
            "t2p2": "Fiya",
            "t2p2flag": "us",
            "t2score": "win",
            "win": "2"
        },
        "l1m2": {
            "t1p1": "Smartyrchild",
            "t1p1flag": "",
            "t1p2": "Quil",
            "t1p2flag": "us",
            "t1score": "2",
            "t2p1": "Juiceman",
            "t2p1flag": "us",
            "t2p2": "Captain Mucinex",
            "t2p2flag": "",
            "t2score": "0",
            "win": "1"
        },
        "l1m3": {
            "t1p1": "Bye",
            "t1p1flag": "",
            "t1p2": "Bye",
            "t1p2flag": "",
            "t1score": "",
            "t2p1": "HRCtypo",
            "t2p1flag": "us",
            "t2p2": "Crimson",
            "t2p2flag": "",
            "t2score": "win",
            "win": "2"
        },
        "l1m4": {
            "t1p1": "Bye",
            "t1p1flag": "",
            "t1p2": "Bye",
            "t1p2flag": "",
            "t1score": "",
            "t2p1": "BIG KID",
            "t2p1flag": "us",
            "t2p2": "r0cket_wizard",
            "t2p2flag": "us",
            "t2score": "win",
            "win": "2"
        },
        "l2m1": {
            "t1p1": "Zanguzen",
            "t1p1flag": "us",
            "t1p2": "Jflex",
            "t1p2flag": "us",
            "t1score": "DQ",
            "t2p1": "SB Noya",
            "t2p1flag": "",
            "t2p2": "Fiya",
            "t2p2flag": "us",
            "t2score": "win",
            "win": "2"
        },
        "l2m2": {
            "t1p1": "Nerd",
            "t1p1flag": "",
            "t1p2": "Subtle",
            "t1p2flag": "us",
            "t1score": "2",
            "t2p1": "Smartyrchild",
            "t2p1flag": "",
            "t2p2": "Quil",
            "t2p2flag": "us",
            "t2score": "0",
            "win": "1"
        },
        "l2m3": {
            "t1p1": "Ryobeat",
            "t1p1flag": "us",
            "t1p2": "Captain Smuckers",
            "t1p2flag": "us",
            "t1score": "2",
            "t2p1": "HRCtypo",
            "t2p1flag": "us",
            "t2p2": "Crimson",
            "t2p2flag": "",
            "t2score": "0",
            "win": "1"
        },
        "l2m4": {
            "t1p1": "Wassabi",
            "t1p1flag": "us",
            "t1p2": "thx",
            "t1p2flag": "",
            "t1score": "2",
            "t2p1": "BIG KID",
            "t2p1flag": "us",
            "t2p2": "r0cket_wizard",
            "t2p2flag": "us",
            "t2score": "0",
            "win": "1"
        },
        "l3m1": {
            "t1p1": "SB Noya",
            "t1p1flag": "",
            "t1p2": "Fiya",
            "t1p2flag": "us",
            "t1score": "2",
            "t2p1": "Nerd",
            "t2p1flag": "",
            "t2p2": "Subtle",
            "t2p2flag": "us",
            "t2score": "0",
            "win": "1"
        },
        "l3m2": {
            "t1p1": "Ryobeat",
            "t1p1flag": "us",
            "t1p2": "Captain Smuckers",
            "t1p2flag": "us",
            "t1score": "2",
            "t2p1": "Wassabi",
            "t2p1flag": "us",
            "t2p2": "thx",
            "t2p2flag": "",
            "t2score": "1",
            "win": "1"
        },
        "l4m1": {
            "t1p1": "DJ Nintendo",
            "t1p1flag": "us",
            "t1p2": "The Moon",
            "t1p2flag": "us",
            "t1score": "3",
            "t2p1": "SB Noya",
            "t2p1flag": "",
            "t2p2": "Fiya",
            "t2p2flag": "us",
            "t2score": "0",
            "win": "1"
        },
        "l4m2": {
            "t1p1": "MrF",
            "t1p1flag": "",
            "t1p2": "Qerb",
            "t1p2flag": "us",
            "t1score": "1",
            "t2p1": "Ryobeat",
            "t2p1flag": "us",
            "t2p2": "Captain Smuckers",
            "t2p2flag": "us",
            "t2score": "3",
            "win": "2"
        }
    },
    "==Winners Bracket==": {
        "r1m1": {
            "t1p1": "DJ Nintendo",
            "t1p1flag": "us",
            "t1p2": "The Moon",
            "t1p2flag": "us",
            "t1score": "win",
            "t2p1": "Bye",
            "t2p1flag": "",
            "t2p2": "Bye",
            "t2p2flag": "",
            "t2score": "",
            "win": "1"
        },
        "r1m2": {
            "t1p1": "SB Noya",
            "t1p1flag": "",
            "t1p2": "Fiya",
            "t1p2flag": "us",
            "t1score": "1",
            "t2p1": "Wassabi",
            "t2p1flag": "us",
            "t2p2": "thx",
            "t2p2flag": "",
            "t2score": "2",
            "win": "2"
        },
        "r1m3": {
            "t1p1": "Ryobeat",
            "t1p1flag": "us",
            "t1p2": "Captain Smuckers",
            "t1p2flag": "us",
            "t1score": "2",
            "t2p1": "Smartyrchild",
            "t2p1flag": "",
            "t2p2": "Quil",
            "t2p2flag": "us",
            "t2score": "0",
            "win": "1"
        },
        "r1m4": {
            "t1p1": "Animal",
            "t1p1flag": "us",
            "t1p2": "G$",
            "t1p2flag": "us",
            "t1score": "2",
            "t2p1": "Juiceman",
            "t2p1flag": "us",
            "t2p2": "Captain Mucinex",
            "t2p2flag": "",
            "t2score": "0",
            "win": "1"
        },
        "r1m5": {
            "t1p1": "Swedish Delight",
            "t1p1flag": "us",
            "t1p2": "Slox",
            "t1p2flag": "us",
            "t1score": "win",
            "t2p1": "Bye",
            "t2p1flag": "",
            "t2p2": "Bye",
            "t2p2flag": "",
            "t2score": "",
            "win": "1"
        },
        "r1m6": {
            "t1p1": "Nerd",
            "t1p1flag": "",
            "t1p2": "Subtle",
            "t1p2flag": "us",
            "t1score": "2",
            "t2p1": "HRCtypo",
            "t2p1flag": "us",
            "t2p2": "Crimson",
            "t2p2flag": "",
            "t2score": "0",
            "win": "1"
        },
        "r1m7": {
            "t1p1": "Zanguzen",
            "t1p1flag": "us",
            "t1p2": "Jflex",
            "t1p2flag": "us",
            "t1score": "win",
            "t2p1": "Bye",
            "t2p1flag": "",
            "t2p2": "Bye",
            "t2p2flag": "",
            "t2score": "",
            "win": "1"
        },
        "r1m8": {
            "t1p1": "MrF",
            "t1p1flag": "",
            "t1p2": "Qerb",
            "t1p2flag": "us",
            "t1score": "2",
            "t2p1": "BIG KID",
            "t2p1flag": "us",
            "t2p2": "r0cket_wizard",
            "t2p2flag": "us",
            "t2score": "0",
            "win": "1"
        },
        "r2m1": {
            "t1p1": "DJ Nintendo",
            "t1p1flag": "us",
            "t1p2": "The Moon",
            "t1p2flag": "us",
            "t1score": "2",
            "t2p1": "Wassabi",
            "t2p1flag": "us",
            "t2p2": "thx",
            "t2p2flag": "",
            "t2score": "0",
            "win": "1"
        },
        "r2m2": {
            "t1p1": "Ryobeat",
            "t1p1flag": "us",
            "t1p2": "Captain Smuckers",
            "t1p2flag": "us",
            "t1score": "1",
            "t2p1": "Animal",
            "t2p1flag": "us",
            "t2p2": "G$",
            "t2p2flag": "us",
            "t2score": "2",
            "win": "2"
        },
        "r2m3": {
            "t1p1": "Swedish Delight",
            "t1p1flag": "us",
            "t1p2": "Slox",
            "t1p2flag": "us",
            "t1score": "2",
            "t2p1": "Nerd",
            "t2p1flag": "",
            "t2p2": "Subtle",
            "t2p2flag": "us",
            "t2score": "0",
            "win": "1"
        },
        "r2m4": {
            "t1p1": "Zanguzen",
            "t1p1flag": "us",
            "t1p2": "Jflex",
            "t1p2flag": "us",
            "t1score": "DQ",
            "t2p1": "MrF",
            "t2p1flag": "",
            "t2p2": "Qerb",
            "t2p2flag": "us",
            "t2score": "win",
            "win": "2"
        },
        "r3m1": {
            "t1p1": "DJ Nintendo",
            "t1p1flag": "us",
            "t1p2": "The Moon",
            "t1p2flag": "us",
            "t1score": "2",
            "t2p1": "Animal",
            "t2p1flag": "us",
            "t2p2": "G$",
            "t2p2flag": "us",
            "t2score": "3",
            "win": "2"
        },
        "r3m2": {
            "t1p1": "Swedish Delight",
            "t1p1flag": "us",
            "t1p2": "Slox",
            "t1p2flag": "us",
            "t1score": "2",
            "t2p1": "MrF",
            "t2p1flag": "",
            "t2p2": "Qerb",
            "t2p2flag": "us",
            "t2score": "0",
            "win": "1"
        }
    }
}